datasette_dashboards/__init__.py
datasette_dashboards/py.typed
datasette_dashboards/static/dashboards.css
datasette_dashboards/static/dashboards.js
datasette_dashboards/static/vega-embed.min.js
datasette_dashboards/static/vega-lite.min.js
datasette_dashboards/static/vega.min.js
datasette_dashboards/templates/dashboard_chart.html
datasette_dashboards/templates/dashboard_list.html
datasette_dashboards/templates/dashboard_view.html
datasette_dashboards-0.7.1.dist-info/LICENSE
datasette_dashboards-0.7.1.dist-info/METADATA
datasette_dashboards-0.7.1.dist-info/WHEEL
datasette_dashboards-0.7.1.dist-info/entry_points.txt
datasette_dashboards-0.7.1.dist-info/RECORD
