Metadata-Version: 2.3
Name: datasette-dashboards
Version: 0.7.1
Summary: Datasette plugin providing data dashboards from metadata
License: Apache License, Version 2.0
Author: Romain Clement
Requires-Python: >=3.9,<3.14
Classifier: License :: Other/Proprietary License
Classifier: Programming Language :: Python :: 3
Classifier: Programming Language :: Python :: 3.9
Classifier: Programming Language :: Python :: 3.10
Classifier: Programming Language :: Python :: 3.11
Classifier: Programming Language :: Python :: 3.12
Classifier: Programming Language :: Python :: 3.13
Requires-Dist: datasette
Requires-Dist: datasette-leaflet
Requires-Dist: datasette-render-markdown
Project-URL: Changelog, https://github.com/rclement/datasette-dashboards/blob/master/CHANGELOG.md
Project-URL: Repository, https://github.com/rclement/datasette-dashboards
